setup.cfg
setup.py
payapp/__init__.py
payapp/classes.py
payapp/payapp.py
payapp.egg-info/PKG-INFO
payapp.egg-info/SOURCES.txt
payapp.egg-info/dependency_links.txt
payapp.egg-info/top_level.txt