Metadata-Version: 1.1
Name: payapp
Version: 1.0.post1
Summary: 모바일 결제 서비스 PayApp의 Python 바인딩
